<?xml version="1.0" encoding="utf-8"?>
<resources name="ru" flag="ru" title="Russian">
	<string_add name="_bx_payment_options_category_general"><![CDATA[Общие]]></string_add>
	<string_add name="_bx_payment_options_category_commissions"><![CDATA[Комиссии]]></string_add>
	<string_add name="_bx_payment_option_inv_issue_day"><![CDATA[День месяца, когда автоматически генерятся счета-фактуры (1, 2, 3 и тп)]]></string_add>
	<string_add name="_bx_payment_option_inv_lifetime"><![CDATA[Срок оплаты - количество дней после даты выставления счета-фактуры]]></string_add>
	<string_add name="_bx_payment_option_inv_expiraction_notify"><![CDATA[За сколько дней до истечения срока оплаты оповестить платильщика]]></string_add>
	<string_add name="_bx_payment_cdt_msg_subscribed"><![CDATA[Спасибо! Подписка создана. Пожалуйста, проверьте ваш email для получения дальнейших инструкций.]]></string_add>

	<string_upd name="_bx_payment_grid_column_title_inv_commissionaire_id"><![CDATA[Получатель]]></string_upd>
	<string_upd name="_bx_payment_grid_column_title_inv_committent_id"><![CDATA[Плательщик]]></string_upd>
	<string_upd name="_bx_payment_popup_title_cms_add"><![CDATA[Добавить ежемесячную комиссию]]></string_upd>
	<string_upd name="_bx_payment_popup_title_cms_edit"><![CDATA[Изменить ежемесячную комиссию]]></string_upd>
	<string_upd name="_bx_payment_form_commissions_input_installment_sys"><![CDATA[Фиксированный взнос]]></string_upd>
	<string_upd name="_bx_payment_form_commissions_input_installment"><![CDATA[Фиксированный взнос]]></string_upd>
	<string_upd name="_bx_payment_et_txt_body_checkout_offline"><![CDATA[{email_header}
<p>Привет,</p>
<p>Пользователь сайта <a href="{profile_link}">{profile_name}</a> хотел заплатить Вам наличными за:</p>
<p>{items}</p>
<p>Сумма: {amount}<br />Дата: {date}</p>
<p>Перейдите на <a href="{pending_orders_link}">страницу неоплаченных заказов</a> для обработки заказа, когда оплата будет получена.</p>
{email_footer}]]></string_upd>
</resources>