<?xml version="1.0" encoding="utf-8"?>
<resources name="ru" flag="ru" title="Russian">
	<string_add name="_bx_antispam_adm_stg_cpt_category_lasso_moderation"><![CDATA[Lasso Moderation]]></string_add>
    <string_add name="_bx_antispam_option_lasso_moderation_enable"><![CDATA[Включить]]></string_add>
    <string_add name="_bx_antispam_option_lasso_moderation_api_key"><![CDATA[Ключ API]]></string_add>
    <string_add name="_bx_antispam_option_lasso_moderation_webhook_secret"><![CDATA[Секрет для вебхука]]></string_add>
    <string_add name="_bx_antispam_option_lasso_moderation_webhook_url"><![CDATA[Вебхук URL]]></string_add>
    <string_add name="_bx_antispam_option_lasso_moderation_action"><![CDATA[Действие]]></string_add>
    <string_add name="_bx_antispam_option_lasso_moderation_action_none"><![CDATA[Нет]]></string_add>
    <string_add name="_bx_antispam_option_lasso_moderation_action_disapprove"><![CDATA[Скрывать]]></string_add>
    <string_add name="_bx_antispam_option_lasso_moderation_report"><![CDATA[Отправлять администратору уведомление о вредоносном контенте]]></string_add>
    <string_add name="_bx_antispam_option_lasso_moderation_threshold_toxicity"><![CDATA[Порог токсичности (0 - 100)]]></string_add>
    <string_add name="_bx_antispam_option_lasso_moderation_threshold_threat"><![CDATA[Порог угрозы (0 - 100)]]></string_add>
    <string_add name="_bx_antispam_option_lasso_moderation_threshold_identity_attack"><![CDATA[Порог атаки на личность (0 - 100)]]></string_add>
    <string_add name="_bx_antispam_option_lasso_moderation_threshold_profanity"><![CDATA[Порог ненормативной лексики (0 - 100)]]></string_add>
    <string_add name="_bx_antispam_et_lasso_moderation_report_name"><![CDATA[Сообщение о размещенном вредоносном контенте]]></string_add>
    <string_add name="_bx_antispam_et_lasso_moderation_report_subject"><![CDATA[Размещен вредоносный контент]]></string_add>
    <string_add name="_bx_antispam_et_lasso_moderation_report_body"><![CDATA[{email_header}
<b>Профиль:</b> <a href="{AuthorUrl}">{AuthorNickName}</a><br />
<bx_if:content_url>
    <b>Ссылка:</b> <a href="{c_url}">{c_url}</a><br /><br />
</bx_if:content_url>
<bx_if:manage_content_url>
    <b>Управлять:</b> <a href="{m_url}">{m_url}</a><br /><br />
</bx_if:manage_content_url>
{email_footer}]]></string_add>
	
	<string_upd name="_bx_antispam_help_text">
      <![CDATA[Этот модуль помогает ограничить спам на сайте. Для этого существуют различные встроенные инструменты:
<ul>
    <li><b>IP table</b> - ручная (раз)блокировка IP</li>
    <li><b>DNSBL</b> - автоматическая блокировка по IP из различных блок-списков</li>
    <li><b>URI DNSBL</b> - автоматическая блокировка спам-контента с помощью спам-URL в тексте</li>
    <li><b>Akismet</b> - автоматическая блокировка спам-контента с использованием <a target="_blank" href="http://akismet.com">Сервиса Akismet</a></li>
    <li><b>StopForumSpam</b> - автоматическая блокировка спам-контента с использованием <a target="_blank" href="http://www.stopforumspam.com">Сервиса StopForumSpam</a></li>
    <li><b>Profanity filter</b> - фильтр ненормативной лексики, основанный на заранее определенных списках слов с возможностью их расширения</a></li>
    <li><b>Toxicity filter</b> - фильтр токсичности, основанный на <a target="_blank" href="https://www.perspectiveapi.com/">Perspective API</a> предоставленном Google</li>
    <li><b>Harmful filter</b> - фильтр вредоносности, основанный на <a target="_blank" href="https://www.lassomoderation.com/">Lasso Moderation API</a></li>
</ul>
]]></string_upd>
</resources>