<?xml version="1.0" encoding="utf-8"?>
<resources name="en" flag="gb" title="English">
	<string_add name="_bx_ads_option_offer_lifetime"><![CDATA[Decline offers automatically after (in hours)]]></string_add>
	<string_add name="_bx_ads_grid_filter_item_title_adm_select_one_filter2"><![CDATA[Any Audience]]></string_add>
	<string_add name="_bx_ads_alert_action_license_register_personal"><![CDATA[Your ad was purchased]]></string_add>
    <string_add name="_bx_ads_txt_ntfs_object_license_register"><![CDATA[<b class="bx-ntfs-content-profile">{owner_name}</b> purchased your ad <b class="bx-ntfs-content-entry">{entry_caption}</b>]]></string_add>
    <string_add name="_bx_ads_alert_action_shipped_personal"><![CDATA[Ad was shipped]]></string_add>
    <string_add name="_bx_ads_txt_ntfs_object_shipped"><![CDATA[<b class="bx-ntfs-content-profile">{owner_name}</b> shipped the ad <b class="bx-ntfs-content-entry">{entry_caption}</b>]]></string_add>
    <string_add name="_bx_ads_alert_action_received_personal"><![CDATA[Ad was received]]></string_add>
    <string_add name="_bx_ads_txt_ntfs_object_received"><![CDATA[<b class="bx-ntfs-content-profile">{owner_name}</b> received the ad <b class="bx-ntfs-content-entry">{entry_caption}</b>]]></string_add>
    <string_add name="_bx_ads_alert_action_offer_added_personal"><![CDATA[Offer was added]]></string_add>
    <string_add name="_bx_ads_txt_ntfs_offer_added"><![CDATA[<b class="bx-ntfs-content-profile">{owner_name}</b> added an offer to your ad <b class="bx-ntfs-content-entry">{entry_caption}</b>]]></string_add>
    <string_add name="_bx_ads_alert_action_offer_accepted_personal"><![CDATA[Offer was accepted]]></string_add>
    <string_add name="_bx_ads_txt_ntfs_offer_accepted"><![CDATA[<b class="bx-ntfs-content-profile">{owner_name}</b> accepted your offer for the ad <b class="bx-ntfs-content-entry">{entry_caption}</b>]]></string_add>
    <string_add name="_bx_ads_alert_action_offer_declined_personal"><![CDATA[Offer was declined]]></string_add>
    <string_add name="_bx_ads_txt_ntfs_offer_declined"><![CDATA[<b class="bx-ntfs-content-profile">{owner_name}</b> declined your offer for the ad <b class="bx-ntfs-content-entry">{entry_caption}</b>]]></string_add>
    <string_add name="_bx_ads_alert_action_offer_canceled_personal"><![CDATA[Offer was canceled]]></string_add>
    <string_add name="_bx_ads_txt_ntfs_offer_canceled"><![CDATA[<b class="bx-ntfs-content-profile">{owner_name}</b> canceled the offer for your ad <b class="bx-ntfs-content-entry">{entry_caption}</b>]]></string_add>
</resources>