<?xml version="1.0" encoding="utf-8"?>
<resources name="ru" flag="ru" title="Russian">
	<string_add name="_bx_courses_page_block_title_sys_joined_entries_summary"><![CDATA[Сводка посещаемых курсов]]></string_add>
	<string_add name="_bx_courses_page_block_title_joined_entries_summary"><![CDATA[Сводка посещаемых курсов]]></string_add>
	<string_add name="_bx_courses_menu_item_title_system_hide_profile"><![CDATA[Скрыть курс]]></string_add>
	<string_add name="_bx_courses_menu_item_title_hide_profile"><![CDATA[Скрыть]]></string_add>
	<string_add name="_bx_courses_menu_item_title_system_unhide_profile"><![CDATA[Показать курс]]></string_add>
	<string_add name="_bx_courses_menu_item_title_unhide_profile"><![CDATA[Публиковать]]></string_add>
	<string_add name="_bx_courses_txt_summary_title"><![CDATA[Прогресс обучения]]></string_add>
	<string_add name="_bx_courses_txt_summary_joined"><![CDATA[Записан на]]></string_add>
	<string_add name="_bx_courses_txt_summary_passed"><![CDATA[Закончено]]></string_add>
	<string_add name="_bx_courses_txt_summary_not_started"><![CDATA[Не начато]]></string_add>

	<string_upd name="_bx_courses_txt_status_hidden"><![CDATA[Этот курс скрыт.]]></string_upd>
</resources>