<?xml version="1.0" encoding="utf-8"?>
<resources name="en" flag="gb" title="English">
	<string_add name="_bx_timeline_menu_item_title_item_share"><![CDATA[Share]]></string_add>
	<string_add name="_bx_timeline_menu_item_title_item_more"><![CDATA[More Actions]]></string_add>

	<string_upd name="_bx_timeline_option_events_per_page_profile"><![CDATA[Number of items on profile page]]></string_upd>
	<string_upd name="_bx_timeline_option_events_per_page_account"><![CDATA[Number of items on dashboard page]]></string_upd>
	<string_upd name="_bx_timeline_option_events_per_page_home"><![CDATA[Number of items on site home page]]></string_upd>
	<string_upd name="_bx_timeline_option_events_per_page"><![CDATA[Number of items per page]]></string_upd>
	<string_upd name="_bx_timeline_txt_sample_comment_single"><![CDATA[comment to timeline post]]></string_upd>
	<string_upd name="_bx_timeline_txt_sample_vote_single"><![CDATA[vote to timeline post]]></string_upd>
	<string_upd name="_bx_timeline_ntfs_txt_object_added"><![CDATA[<b class="bx-ntfs-content-profile">{owner_name}</b> added a {entry_sample} <b class="bx-ntfs-content-entry">{entry_caption}</b>]]></string_upd>
	<string_upd name="_bx_timeline_txt_object_reposted"><![CDATA[<b class="bx-ntfs-content-profile">{owner_name}</b> reposted a {entry_sample} <b class="bx-ntfs-content-entry">{entry_caption}</b>]]></string_upd>
</resources>