<?xml version="1.0" encoding="utf-8"?>
<resources name="en" flag="gb" title="English">
	<string_add name="_bx_payment_et_txt_name_wrong_balance"><![CDATA[Insufficient funds to write off.]]></string_add>
    <string_add name="_bx_payment_et_txt_subject_wrong_balance"><![CDATA[Insufficient funds to write off.]]></string_add>
    <string_add name="_bx_payment_et_txt_body_wrong_balance"><![CDATA[{email_header}
<p>Hello,</p>
<p>You have insufficient funds to write off for paying a subscription.</p>
<p>Subscription info:<br />ID: {sibscription_id}<br />Customer: {sibscription_customer}<br />Payment provider: {sibscription_provider}<br />Date: {sibscription_date}</p>
{email_footer}]]></string_add>
	<string_add name="_bx_payment_cdt_err_wrong_balance"><![CDATA[Insufficient funds to write off.]]></string_add>
</resources>